nimbus/__init__.py
nimbus/accum.py
nimbus/acurite.py
nimbus/device.py
nimbus/engine.py
nimbus/events.py
nimbus/formulas.py
nimbus/rest.py
nimbus/services.py
nimbus/simulator.py
nimbus/units.py
nimbus/util.py
nimbus/vantage.py
nimbus_pws-1.0.49.data/scripts/nimbus
nimbus_pws-1.0.49.dist-info/METADATA
nimbus_pws-1.0.49.dist-info/WHEEL
nimbus_pws-1.0.49.dist-info/namespace_packages.txt
nimbus_pws-1.0.49.dist-info/top_level.txt
nimbus_pws-1.0.49.dist-info/zip-safe
nimbus_pws-1.0.49.dist-info/RECORD
