Metadata-Version: 2.1
Name: nimbus-pws
Version: 1.0.49
Summary: weather software
Home-page: 
Author: Garret Hayes
Author-email: glhayes81@gmail.com
Maintainer: 
Maintainer-email: 
License: GPLv3
Classifier: Development Status :: 3 - Alpha
Classifier: Programming Language :: Python
Requires-Dist: configobj
Requires-Dist: pyserial
Requires-Dist: pyusb
Requires-Dist: requests
Requires-Dist: sentry-sdk
Requires-Dist: setuptools
Requires-Dist: urllib3
